HTTP_Request_Randomizer-0.0.5.dist-info/.PKG-INFO.swp
HTTP_Request_Randomizer-0.0.5.dist-info/DESCRIPTION.rst
HTTP_Request_Randomizer-0.0.5.dist-info/METADATA
HTTP_Request_Randomizer-0.0.5.dist-info/RECORD
HTTP_Request_Randomizer-0.0.5.dist-info/WHEEL
HTTP_Request_Randomizer-0.0.5.dist-info/metadata.json
HTTP_Request_Randomizer-0.0.5.dist-info/top_level.txt
http/__init__.py
http/requests/__init__.py
http/requests/data/user_agents.txt
http/requests/errors/ParserExceptions.py
http/requests/errors/__init__.py
http/requests/parsers/UrlParser.py
http/requests/parsers/__init__.py
http/requests/parsers/freeproxyParser.py
http/requests/parsers/proxyforeuParser.py
http/requests/parsers/rebroweeblyParser.py
http/requests/parsers/samairproxyParser.py
http/requests/proxy/__init__.py
http/requests/proxy/requestProxy.py
http/requests/useragent/__init__.py
http/requests/useragent/userAgent.py
project/__init__.py
project/http/__init__.py
project/http/requests/__init__.py
project/http/requests/errors/ParserExceptions.py
project/http/requests/errors/__init__.py
project/http/requests/parsers/UrlParser.py
project/http/requests/parsers/__init__.py
project/http/requests/parsers/freeproxyParser.py
project/http/requests/parsers/proxyforeuParser.py
project/http/requests/parsers/rebroweeblyParser.py
project/http/requests/parsers/samairproxyParser.py
project/http/requests/proxy/__init__.py
project/http/requests/proxy/requestProxy.py
project/http/requests/useragent/__init__.py
project/http/requests/useragent/userAgent.py
project/tests/__init__.py
project/tests/test_parsers.py
