Metadata-Version: 2.0
Name: HTTP-Request-Randomizer
Version: 0.0.5
Summary: A package using public proxies to randomise http requests.
Home-page: https://pgaref.github.io/blog/python-proxy/
Author: pgaref
Author-email: pangaref@gmail.com
License: MIT
Platform: UNKNOWN
Requires-Dist: bs4
Requires-Dist: httmock
Requires-Dist: psutil
Requires-Dist: python-dateutil
Requires-Dist: requests
Requires-Dist: schedule
